keras_lookahead
tests
