Metadata-Version: 2.1
Name: keras-lookahead
Version: 0.6.0
Summary: Lookahead mechanism for optimizers in Keras
Home-page: https://github.com/CyberZHG/keras-lookahead
Author: CyberZHG
Author-email: CyberZHG@users.noreply.github.com
License: MIT
Platform: UNKNOWN
Classifier: Programming Language :: Python :: 3.6
Classifier: License :: OSI Approved :: MIT License
Classifier: Operating System :: OS Independent
